src/__init__.py
src/main.py
src/cli/__init__.py
src/cli/commands.py
src/cli/handler.py
src/cli/parser.py
src/config/__init__.py
src/config/config.py
src/llm_integration/__init__.py
src/llm_integration/openai_integration.py
bash_buddy_cli-0.1.5.dist-info/LICENSE.md
bash_buddy_cli-0.1.5.dist-info/METADATA
bash_buddy_cli-0.1.5.dist-info/WHEEL
bash_buddy_cli-0.1.5.dist-info/entry_points.txt
bash_buddy_cli-0.1.5.dist-info/top_level.txt
bash_buddy_cli-0.1.5.dist-info/RECORD
