Metadata-Version: 2.1
Name: bash_buddy_cli
Version: 0.1.5
Summary: A CLI tool for interacting with Meta Ads API
Home-page: https://github.com/TheRealJamesRussell/BashBuddy
Author: TheRealJamesRussell
Author-email: nope@example.com
Classifier: Programming Language :: Python :: 3
Classifier: License :: OSI Approved :: GNU General Public License v3 (GPLv3)
Classifier: Operating System :: OS Independent
Requires-Python: >=3.6
License-File: LICENSE.md
Requires-Dist: python-dotenv
Requires-Dist: openai==1.43.0
Provides-Extra: dev
Requires-Dist: setuptools==74.1.1; extra == "dev"
Requires-Dist: wheel==0.44.0; extra == "dev"
Requires-Dist: twine==5.1.1; extra == "dev"
